asos/__init__.py
asos/__main__.py
asos/asos.py
asos-1.0.8.dist-info/LICENSE
asos-1.0.8.dist-info/METADATA
asos-1.0.8.dist-info/WHEEL
asos-1.0.8.dist-info/top_level.txt
asos-1.0.8.dist-info/RECORD
