Metadata-Version: 2.1
Name: asos
Version: 1.0.8
Summary: A scheduler of stuff (ASOS)
Home-page: https://github.com/python-asos/
Author: Pavel Kim
Author-email: hello@pavelkim.ru
License: UNKNOWN
Platform: UNKNOWN
Classifier: Programming Language :: Python :: 3
Classifier: License :: OSI Approved :: GNU General Public License v3 (GPLv3)
Classifier: Operating System :: OS Independent
Requires-Python: >=3.6
